tsfm/__init__.py
tsfm/data.py
tsfm/exceptions.py
tsfm/outputs.py
tsfm/py.typed
tsfm/models/__init__.py
tsfm/models/armodel.py
tsfm/models/base.py
tsfm/models/chronos.py
tsfm/models/chronos2.py
tsfm/models/moirai.py
tsfm/models/moirai2.py
tsfmecb-1.0.5.dist-info/METADATA
tsfmecb-1.0.5.dist-info/WHEEL
tsfmecb-1.0.5.dist-info/RECORD
