Metadata-Version: 2.4
Name: tsfmecb
Version: 1.0.5
Summary: tsfm provides an easy interface to use TimeSeries Foundational Models.
Author-email: Ilias Aarab <ilias.aarab@ecb.europa.eu>
Requires-Python: >=3.12
Requires-Dist: accelerate>=1.10.1
Requires-Dist: chronos-forecasting>=2.0
Requires-Dist: gluonts[torch]
Requires-Dist: matplotlib>=3.8
Requires-Dist: numpy
Requires-Dist: pandas
Requires-Dist: scienceplots>=2.1.1
Requires-Dist: scipy>=1.11.4
Requires-Dist: statsmodels>=0.14.5
Requires-Dist: torch
Requires-Dist: transformers>=4.54.1
Requires-Dist: uni2ts>=2.0.0
